__pyinstaller/__init__.py
__pyinstaller/hook-deltarune_rando_patcher.py
DeltapatcherForDeltarando-1.0.1.dist-info/LICENSE.txt
DeltapatcherForDeltarando-1.0.1.dist-info/METADATA
DeltapatcherForDeltarando-1.0.1.dist-info/NOTICE.txt
DeltapatcherForDeltarando-1.0.1.dist-info/WHEEL
DeltapatcherForDeltarando-1.0.1.dist-info/entry_points.txt
DeltapatcherForDeltarando-1.0.1.dist-info/top_level.txt
DeltapatcherForDeltarando-1.0.1.dist-info/RECORD
