Metadata-Version: 2.1
Name: DeltapatcherForDeltarando
Version: 1.0.1
Summary: DELTARUNE Randovania Patcher
Home-page: https://github.com/jonloveslegos/DeltapatcherForDELTARUNERandovania
Author: jonloveslegos
Author-email: <jonloveslegos@email.com>
License: UNKNOWN
Platform: UNKNOWN
Classifier: License :: OSI Approved :: GNU General Public License v3 (GPLv3)
Classifier: Development Status :: 3 - Alpha
Classifier: Intended Audience :: Developers
Classifier: Programming Language :: Python :: 3.9
Requires-Python: >=3.9
License-File: LICENSE.txt
License-File: NOTICE.txt
Requires-Dist: mercury-engine-data-structures (>=0.12.0)
Requires-Dist: jsonschema (>=4.0.0)
Requires-Dist: ips.py (>=0.1.2)
Provides-Extra: test
Requires-Dist: pytest ; extra == 'test'
Requires-Dist: pytest-cov ; extra == 'test'
Requires-Dist: pytest-mock ; extra == 'test'
